thunderfish/__init__.py
thunderfish/bestwindow.py
thunderfish/checkpulse.py
thunderfish/chirp.py
thunderfish/collectfish.py
thunderfish/consistentfishes.py
thunderfish/efield.py
thunderfish/eodanalysis.py
thunderfish/eodexplorer.py
thunderfish/fakefish.py
thunderfish/fishfinder.py
thunderfish/fishshapes.py
thunderfish/harmonics.py
thunderfish/hopkinsloader.py
thunderfish/pulseplots.py
thunderfish/pulses.py
thunderfish/pulsetracker.py
thunderfish/thunderbrowse.py
thunderfish/thunderfish.py
thunderfish/thunderlogger.py
thunderfish/version.py
thunderfish-2.0.0.dist-info/LICENSE
thunderfish-2.0.0.dist-info/METADATA
thunderfish-2.0.0.dist-info/WHEEL
thunderfish-2.0.0.dist-info/entry_points.txt
thunderfish-2.0.0.dist-info/top_level.txt
thunderfish-2.0.0.dist-info/RECORD
