Metadata-Version: 2.1
Name: thunderfish
Version: 2.0.0
Summary: Algorithms and scripts for analyzing recordings of electric fish waveforms.
Author: Juan F. Sehuanes, Till Raab, Jörg Henninger, Jan Grewe, Liz Weerdmeester
Author-email: Jan Benda <jan.benda@uni-tuebingen.de>
Maintainer-email: Jan Benda <jan.benda@uni-tuebingen.de>
License: GNU GENERAL PUBLIC LICENSE
Project-URL: Repository, https://github.com/bendalab/thunderfish
Project-URL: Documentation, https://bendalab.github.io/thunderfish
Classifier: Development Status :: 4 - Beta
Classifier: Environment :: Console
Classifier: Intended Audience :: Science/Research
Classifier: License :: OSI Approved :: GNU General Public License v3 (GPLv3)
Classifier: Natural Language :: English
Classifier: Programming Language :: Python :: 3
Classifier: Programming Language :: Python :: 3.8
Classifier: Programming Language :: Python :: 3.12
Classifier: Operating System :: OS Independent
Classifier: Topic :: Multimedia :: Sound/Audio
Classifier: Topic :: Multimedia :: Sound/Audio :: Analysis
Classifier: Topic :: Multimedia :: Sound/Audio :: Conversion
Classifier: Topic :: Scientific/Engineering
Classifier: Topic :: Software Development :: Libraries :: Python Modules
Requires-Python: >=3.6
License-File: LICENSE
Requires-Dist: scikit-learn
Requires-Dist: scipy
Requires-Dist: numpy
Requires-Dist: matplotlib
Requires-Dist: thunderlab
